{
  "packages": [
    {
      "name": "renesas-re",
      "maintainer": "SHCVN",
      "websiteURL": "",
      "email": "",
      "help": {
        "online": ""
      },
      "platforms": [
        {
          "name": "RE01 Boards",
          "architecture": "re01",
          "version": "1.0.0",
          "category": "renesas re family",
          "url": "https://github.com/VietNg2702/Repository/blob/main/RE01_100.zip?raw=true",
          "archiveFileName": "RE01_100.zip",
          "checksum": "SHA-256:1638389ec880a747592dd89f96408551163845b35a587d6ddfb6f385facb3ff0",
          "size": "832162",
          "boards": [
            {"name": "EK-RE01-256KB"}
          ],
          "toolsDependencies": [
            {
              "packager": "renesas-re", 
              "version": "6-2017-q2-update", 
              "name": "arm-none-eabi-gcc"
            }
          ]
        }
        ],
      "tools": [
        {
            "version": "6-2017-q2-update",
            "name": "arm-none-eabi-gcc",
            "systems": [
            {
              "host": "i686-mingw32",
              "url": "https://developer.arm.com/-/media/Files/downloads/gnu-rm/6-2017q2/gcc-arm-none-eabi-6-2017-q2-update-win32.zip?revision=d8809bf7-a431-49ee-98d5-0475d839f8f1?product=GNU%20Arm%20Embedded%20Toolchain%20Downloads,ZIP,,Windows,6-2017-q2-update",
              "archiveFileName": "gcc-arm-none-eabi-6-2017-q2-update-win32.zip",
              "checksum": "MD5:df6c2f763a6114c951e3f1e509af3cbc",
              "size": "131285223"
            }
        ]
        }
      ]
    }
    ]
  
}
  
  